[
	{
		"accessSource" : "",
		"addType" : "",
		"cameraFunctions" : "",
		"cameraType" : "1",
		"category" : "1",
		"channelCode" : "32021154001320010163",
		"channelId" : "32021154001320010163",
		"channelName" : "蠡湖壹号馨苑南门人脸-ZH20",
		"channelSeq" : 0,
		"channelSn" : "32021154001320010163",
		"channelType" : "1",
		"children" : [],
		"deviceCode" : "32021154001320010163D",
		"domain" : true,
		"domainId" : 4,
		"fullCheck" : true,
		"gpsX" : "120.259012000000",
		"gpsY" : "31.527376000000",
		"halfCheck" : false,
		"icon" : "rifle_channel",
		"id" : "32021154001320010163",
		"intelliState" : 0,
		"isFullCheck" : true,
		"isHalfCheck" : false,
		"isOnline" : true,
		"isParent" : false,
		"isSearched" : true,
		"mapType" : "",
		"name" : "蠡湖壹号馨苑南门人脸-ZH20",
		"nodeType" : 3,
		"notEnableEncoderChannel" : false,
		"online" : "1",
		"orgCode" : "32021154002160010163",
		"orgType" : "1",
		"paasId" : "152272379",
		"parent" : false,
		"parentId" : "32021154001320010163D",
		"parentNodeType" : 0,
		"platformCode" : "84816576869850244",
		"resourceCode" : "32021154001320010163",
		"resourceName" : "蠡湖壹号馨苑南门人脸-ZH20",
		"sn" : "32021154001320010163",
		"sort" : 0,
		"stat" : 1,
		"status" : 1,
		"statusTime" : 1691123216000,
		"subCount" : 0,
		"subType" : "2",
		"unitType" : "1"
	},
	{
		"accessSource" : "",
		"addType" : "",
		"cameraFunctions" : "",
		"cameraType" : "1",
		"category" : "1",
		"channelCode" : "32021154001320016009",
		"channelId" : "32021154001320016009",
		"channelName" : "蠡湖壹号馨苑南门车辆-ZH20",
		"channelSeq" : 0,
		"channelSn" : "32021154001320016009",
		"channelType" : "1",
		"children" : [],
		"deviceCode" : "32021154001320016009D",
		"domain" : true,
		"domainId" : 4,
		"fullCheck" : true,
		"gpsX" : "120.259022000000",
		"gpsY" : "31.527360000000",
		"halfCheck" : false,
		"icon" : "rifle_channel",
		"id" : "32021154001320016009",
		"intelliState" : 0,
		"isFullCheck" : true,
		"isHalfCheck" : false,
		"isOnline" : true,
		"isParent" : false,
		"isSearched" : true,
		"mapType" : "",
		"name" : "蠡湖壹号馨苑南门车辆-ZH20",
		"nodeType" : 3,
		"notEnableEncoderChannel" : false,
		"online" : "1",
		"orgCode" : "32021154002160010163",
		"orgType" : "1",
		"paasId" : "152272379",
		"parent" : false,
		"parentId" : "32021154001320016009D",
		"parentNodeType" : 0,
		"platformCode" : "84816576869850244",
		"resourceCode" : "32021154001320016009",
		"resourceName" : "蠡湖壹号馨苑南门车辆-ZH20",
		"sn" : "32021154001320016009",
		"sort" : 0,
		"stat" : 1,
		"status" : 1,
		"statusTime" : 1692529343000,
		"subCount" : 0,
		"subType" : "2",
		"unitType" : "1"
	},
	{
		"accessSource" : "",
		"addType" : "",
		"cameraFunctions" : "",
		"cameraType" : "1",
		"category" : "1",
		"channelCode" : "32021154001320017207",
		"channelId" : "32021154001320017207",
		"channelName" : "蠡湖壹号馨苑南门枪机-ZH20",
		"channelSeq" : 0,
		"channelSn" : "32021154001320017207",
		"channelType" : "1",
		"children" : [],
		"deviceCode" : "32021154001320017207D",
		"domain" : true,
		"domainId" : 4,
		"fullCheck" : true,
		"gpsX" : "120.259044000000",
		"gpsY" : "31.527370000000",
		"halfCheck" : false,
		"icon" : "rifle_channel",
		"id" : "32021154001320017207",
		"intelliState" : 0,
		"isFullCheck" : true,
		"isHalfCheck" : false,
		"isOnline" : true,
		"isParent" : false,
		"isSearched" : true,
		"mapType" : "",
		"name" : "蠡湖壹号馨苑南门枪机-ZH20",
		"nodeType" : 3,
		"notEnableEncoderChannel" : false,
		"online" : "1",
		"orgCode" : "32021154002160010163",
		"orgType" : "1",
		"paasId" : "152272379",
		"parent" : false,
		"parentId" : "32021154001320017207D",
		"parentNodeType" : 0,
		"platformCode" : "84816576869850244",
		"resourceCode" : "32021154001320017207",
		"resourceName" : "蠡湖壹号馨苑南门枪机-ZH20",
		"sn" : "32021154001320017207",
		"sort" : 0,
		"stat" : 1,
		"status" : 1,
		"statusTime" : 1691123216000,
		"subCount" : 0,
		"subType" : "2",
		"unitType" : "1"
	},
	{
		"accessSource" : "",
		"addType" : "",
		"cameraFunctions" : "",
		"cameraType" : "1",
		"category" : "1",
		"channelCode" : "32021154001320010380",
		"channelId" : "32021154001320010380",
		"channelName" : "天竺花苑B区经贸路西北门车辆-ZH20",
		"channelSeq" : 0,
		"channelSn" : "32021154001320010380",
		"channelType" : "1",
		"children" : [],
		"deviceCode" : "32021154001320010380D",
		"domain" : true,
		"domainId" : 4,
		"fullCheck" : true,
		"gpsX" : "120.271440000000",
		"gpsY" : "31.528959000000",
		"halfCheck" : false,
		"icon" : "rifle_channel",
		"id" : "32021154001320010380",
		"intelliState" : 0,
		"isFullCheck" : true,
		"isHalfCheck" : false,
		"isOnline" : true,
		"isParent" : false,
		"isSearched" : true,
		"mapType" : "",
		"name" : "天竺花苑B区经贸路西北门车辆-ZH20",
		"nodeType" : 3,
		"notEnableEncoderChannel" : false,
		"online" : "1",
		"orgCode" : "32021154002160010380",
		"orgType" : "1",
		"paasId" : "152272379",
		"parent" : false,
		"parentId" : "32021154001320010380D",
		"parentNodeType" : 0,
		"platformCode" : "84816576869850244",
		"resourceCode" : "32021154001320010380",
		"resourceName" : "天竺花苑B区经贸路西北门车辆-ZH20",
		"sn" : "32021154001320010380",
		"sort" : 0,
		"stat" : 1,
		"status" : 1,
		"statusTime" : 1691924550000,
		"subCount" : 0,
		"subType" : "2",
		"unitType" : "1"
	},
	{
		"accessSource" : "",
		"addType" : "",
		"cameraFunctions" : "",
		"cameraType" : "1",
		"category" : "1",
		"channelCode" : "32021154001320010993",
		"channelId" : "32021154001320010993",
		"channelName" : "天竺花苑B区经贸路西南门人脸-ZH20",
		"channelSeq" : 0,
		"channelSn" : "32021154001320010993",
		"channelType" : "1",
		"children" : [],
		"deviceCode" : "32021154001320010993D",
		"domain" : true,
		"domainId" : 4,
		"fullCheck" : true,
		"gpsX" : "120.271672000000",
		"gpsY" : "31.527897000000",
		"halfCheck" : false,
		"icon" : "rifle_channel",
		"id" : "32021154001320010993",
		"intelliState" : 0,
		"isFullCheck" : true,
		"isHalfCheck" : false,
		"isOnline" : true,
		"isParent" : false,
		"isSearched" : true,
		"mapType" : "",
		"name" : "天竺花苑B区经贸路西南门人脸-ZH20",
		"nodeType" : 3,
		"notEnableEncoderChannel" : false,
		"online" : "1",
		"orgCode" : "32021154002160010380",
		"orgType" : "1",
		"paasId" : "152272379",
		"parent" : false,
		"parentId" : "32021154001320010993D",
		"parentNodeType" : 0,
		"platformCode" : "84816576869850244",
		"resourceCode" : "32021154001320010993",
		"resourceName" : "天竺花苑B区经贸路西南门人脸-ZH20",
		"sn" : "32021154001320010993",
		"sort" : 0,
		"stat" : 1,
		"status" : 1,
		"statusTime" : 1691123216000,
		"subCount" : 0,
		"subType" : "2",
		"unitType" : "1"
	},
	{
		"accessSource" : "",
		"addType" : "",
		"cameraFunctions" : "",
		"cameraType" : "1",
		"category" : "1",
		"channelCode" : "32021154001320013716",
		"channelId" : "32021154001320013716",
		"channelName" : "天竺花苑B区经贸路西北门双仓人脸-ZH20",
		"channelSeq" : 0,
		"channelSn" : "32021154001320013716",
		"channelType" : "1",
		"children" : [],
		"deviceCode" : "32021154001320013716D",
		"domain" : true,
		"domainId" : 4,
		"fullCheck" : true,
		"gpsX" : "120.271447000000",
		"gpsY" : "31.528991000000",
		"halfCheck" : false,
		"icon" : "rifle_channel",
		"id" : "32021154001320013716",
		"intelliState" : 0,
		"isFullCheck" : true,
		"isHalfCheck" : false,
		"isOnline" : true,
		"isParent" : false,
		"isSearched" : true,
		"mapType" : "",
		"name" : "天竺花苑B区经贸路西北门双仓人脸-ZH20",
		"nodeType" : 3,
		"notEnableEncoderChannel" : false,
		"online" : "1",
		"orgCode" : "32021154002160010380",
		"orgType" : "1",
		"paasId" : "152272379",
		"parent" : false,
		"parentId" : "32021154001320013716D",
		"parentNodeType" : 0,
		"platformCode" : "84816576869850244",
		"resourceCode" : "32021154001320013716",
		"resourceName" : "天竺花苑B区经贸路西北门双仓人脸-ZH20",
		"sn" : "32021154001320013716",
		"sort" : 0,
		"stat" : 1,
		"status" : 1,
		"statusTime" : 1691924550000,
		"subCount" : 0,
		"subType" : "2",
		"unitType" : "1"
	},
	{
		"accessSource" : "",
		"addType" : "",
		"cameraFunctions" : "",
		"cameraType" : "1",
		"category" : "1",
		"channelCode" : "32021154001320014480",
		"channelId" : "32021154001320014480",
		"channelName" : "天竺花苑B区经贸路西北门双仓-ZH20",
		"channelSeq" : 0,
		"channelSn" : "32021154001320014480",
		"channelType" : "1",
		"children" : [],
		"deviceCode" : "32021154001320014480D",
		"domain" : true,
		"domainId" : 4,
		"fullCheck" : true,
		"gpsX" : "120.271431000000",
		"gpsY" : "31.528981000000",
		"halfCheck" : false,
		"icon" : "rifle_channel",
		"id" : "32021154001320014480",
		"intelliState" : 0,
		"isFullCheck" : true,
		"isHalfCheck" : false,
		"isOnline" : true,
		"isParent" : false,
		"isSearched" : true,
		"mapType" : "",
		"name" : "天竺花苑B区经贸路西北门双仓-ZH20",
		"nodeType" : 3,
		"notEnableEncoderChannel" : false,
		"online" : "1",
		"orgCode" : "32021154002160010380",
		"orgType" : "1",
		"paasId" : "152272379",
		"parent" : false,
		"parentId" : "32021154001320014480D",
		"parentNodeType" : 0,
		"platformCode" : "84816576869850244",
		"resourceCode" : "32021154001320014480",
		"resourceName" : "天竺花苑B区经贸路西北门双仓-ZH20",
		"sn" : "32021154001320014480",
		"sort" : 0,
		"stat" : 1,
		"status" : 1,
		"statusTime" : 1691924550000,
		"subCount" : 0,
		"subType" : "2",
		"unitType" : "1"
	},
	{
		"accessSource" : "",
		"addType" : "",
		"cameraFunctions" : "",
		"cameraType" : "1",
		"category" : "1",
		"channelCode" : "32021154001320017083",
		"channelId" : "32021154001320017083",
		"channelName" : "天竺花苑B区经贸路西南门车辆-ZH20",
		"channelSeq" : 0,
		"channelSn" : "32021154001320017083",
		"channelType" : "1",
		"children" : [],
		"deviceCode" : "32021154001320017083D",
		"domain" : true,
		"domainId" : 4,
		"fullCheck" : true,
		"gpsX" : "120.271671000000",
		"gpsY" : "31.527923000000",
		"halfCheck" : false,
		"icon" : "rifle_channel",
		"id" : "32021154001320017083",
		"intelliState" : 0,
		"isFullCheck" : true,
		"isHalfCheck" : false,
		"isOnline" : true,
		"isParent" : false,
		"isSearched" : true,
		"mapType" : "",
		"name" : "天竺花苑B区经贸路西南门车辆-ZH20",
		"nodeType" : 3,
		"notEnableEncoderChannel" : false,
		"online" : "1",
		"orgCode" : "32021154002160010380",
		"orgType" : "1",
		"paasId" : "152272379",
		"parent" : false,
		"parentId" : "32021154001320017083D",
		"parentNodeType" : 0,
		"platformCode" : "84816576869850244",
		"resourceCode" : "32021154001320017083",
		"resourceName" : "天竺花苑B区经贸路西南门车辆-ZH20",
		"sn" : "32021154001320017083",
		"sort" : 0,
		"stat" : 1,
		"status" : 1,
		"statusTime" : 1691123216000,
		"subCount" : 0,
		"subType" : "2",
		"unitType" : "1"
	},
	{
		"accessSource" : "",
		"addType" : "",
		"cameraFunctions" : "",
		"cameraType" : "1",
		"category" : "1",
		"channelCode" : "32021154001320019872",
		"channelId" : "32021154001320019872",
		"channelName" : "天竺花苑B区经贸路西南门枪机-ZH20",
		"channelSeq" : 0,
		"channelSn" : "32021154001320019872",
		"channelType" : "1",
		"children" : [],
		"deviceCode" : "32021154001320019872D",
		"domain" : true,
		"domainId" : 4,
		"fullCheck" : true,
		"gpsX" : "120.271687000000",
		"gpsY" : "31.527913000000",
		"halfCheck" : false,
		"icon" : "rifle_channel",
		"id" : "32021154001320019872",
		"intelliState" : 0,
		"isFullCheck" : true,
		"isHalfCheck" : false,
		"isOnline" : true,
		"isParent" : false,
		"isSearched" : true,
		"mapType" : "",
		"name" : "天竺花苑B区经贸路西南门枪机-ZH20",
		"nodeType" : 3,
		"notEnableEncoderChannel" : false,
		"online" : "1",
		"orgCode" : "32021154002160010380",
		"orgType" : "1",
		"paasId" : "152272379",
		"parent" : false,
		"parentId" : "32021154001320019872D",
		"parentNodeType" : 0,
		"platformCode" : "84816576869850244",
		"resourceCode" : "32021154001320019872",
		"resourceName" : "天竺花苑B区经贸路西南门枪机-ZH20",
		"sn" : "32021154001320019872",
		"sort" : 0,
		"stat" : 1,
		"status" : 1,
		"statusTime" : 1691123216000,
		"subCount" : 0,
		"subType" : "2",
		"unitType" : "1"
	},
	{
		"accessSource" : "",
		"addType" : "",
		"cameraFunctions" : "",
		"cameraType" : "1",
		"category" : "1",
		"channelCode" : "32021154001320010379",
		"channelId" : "32021154001320010379",
		"channelName" : "瑞湖华庭一期北门车辆-ZH20",
		"channelSeq" : 0,
		"channelSn" : "32021154001320010379",
		"channelType" : "1",
		"children" : [],
		"deviceCode" : "32021154001320010379D",
		"domain" : true,
		"domainId" : 4,
		"fullCheck" : true,
		"gpsX" : "120.256180000000",
		"gpsY" : "31.536377000000",
		"halfCheck" : false,
		"icon" : "rifle_channel",
		"id" : "32021154001320010379",
		"intelliState" : 0,
		"isFullCheck" : true,
		"isHalfCheck" : false,
		"isOnline" : true,
		"isParent" : false,
		"isSearched" : true,
		"mapType" : "",
		"name" : "瑞湖华庭一期北门车辆-ZH20",
		"nodeType" : 3,
		"notEnableEncoderChannel" : false,
		"online" : "1",
		"orgCode" : "32021154002160010968",
		"orgType" : "1",
		"paasId" : "152272379",
		"parent" : false,
		"parentId" : "32021154001320010379D",
		"parentNodeType" : 0,
		"platformCode" : "84816576869850244",
		"resourceCode" : "32021154001320010379",
		"resourceName" : "瑞湖华庭一期北门车辆-ZH20",
		"sn" : "32021154001320010379",
		"sort" : 0,
		"stat" : 1,
		"status" : 1,
		"statusTime" : 1691123216000,
		"subCount" : 0,
		"subType" : "2",
		"unitType" : "1"
	},
	{
		"accessSource" : "",
		"addType" : "",
		"cameraFunctions" : "",
		"cameraType" : "1",
		"category" : "1",
		"channelCode" : "32021154001320010968",
		"channelId" : "32021154001320010968",
		"channelName" : "瑞湖华庭一期南门车辆-ZH20",
		"channelSeq" : 0,
		"channelSn" : "32021154001320010968",
		"channelType" : "1",
		"children" : [],
		"deviceCode" : "32021154001320010968D",
		"domain" : true,
		"domainId" : 4,
		"fullCheck" : true,
		"gpsX" : "120.256185000000",
		"gpsY" : "31.535958000000",
		"halfCheck" : false,
		"icon" : "rifle_channel",
		"id" : "32021154001320010968",
		"intelliState" : 0,
		"isFullCheck" : true,
		"isHalfCheck" : false,
		"isOnline" : true,
		"isParent" : false,
		"isSearched" : true,
		"mapType" : "",
		"name" : "瑞湖华庭一期南门车辆-ZH20",
		"nodeType" : 3,
		"notEnableEncoderChannel" : false,
		"online" : "1",
		"orgCode" : "32021154002160010968",
		"orgType" : "1",
		"paasId" : "152272379",
		"parent" : false,
		"parentId" : "32021154001320010968D",
		"parentNodeType" : 0,
		"platformCode" : "84816576869850244",
		"resourceCode" : "32021154001320010968",
		"resourceName" : "瑞湖华庭一期南门车辆-ZH20",
		"sn" : "32021154001320010968",
		"sort" : 0,
		"stat" : 1,
		"status" : 1,
		"statusTime" : 1692579465000,
		"subCount" : 0,
		"subType" : "2",
		"unitType" : "1"
	},
	{
		"accessSource" : "",
		"addType" : "",
		"cameraFunctions" : "",
		"cameraType" : "1",
		"category" : "1",
		"channelCode" : "32021154001320012081",
		"channelId" : "32021154001320012081",
		"channelName" : "瑞湖华庭一期北门双仓人脸-ZH20",
		"channelSeq" : 0,
		"channelSn" : "32021154001320012081",
		"channelType" : "1",
		"children" : [],
		"deviceCode" : "32021154001320012081D",
		"domain" : true,
		"domainId" : 4,
		"fullCheck" : true,
		"gpsX" : "120.256206000000",
		"gpsY" : "31.536329000000",
		"halfCheck" : false,
		"icon" : "rifle_channel",
		"id" : "32021154001320012081",
		"intelliState" : 0,
		"isFullCheck" : true,
		"isHalfCheck" : false,
		"isOnline" : true,
		"isParent" : false,
		"isSearched" : true,
		"mapType" : "",
		"name" : "瑞湖华庭一期北门双仓人脸-ZH20",
		"nodeType" : 3,
		"notEnableEncoderChannel" : false,
		"online" : "1",
		"orgCode" : "32021154002160010968",
		"orgType" : "1",
		"paasId" : "152272379",
		"parent" : false,
		"parentId" : "32021154001320012081D",
		"parentNodeType" : 0,
		"platformCode" : "84816576869850244",
		"resourceCode" : "32021154001320012081",
		"resourceName" : "瑞湖华庭一期北门双仓人脸-ZH20",
		"sn" : "32021154001320012081",
		"sort" : 0,
		"stat" : 1,
		"status" : 1,
		"statusTime" : 1691123216000,
		"subCount" : 0,
		"subType" : "2",
		"unitType" : "1"
	},
	{
		"accessSource" : "",
		"addType" : "",
		"cameraFunctions" : "",
		"cameraType" : "1",
		"category" : "1",
		"channelCode" : "32021154001320012820",
		"channelId" : "32021154001320012820",
		"channelName" : "瑞湖华庭二期南门车辆-ZH20",
		"channelSeq" : 0,
		"channelSn" : "32021154001320012820",
		"channelType" : "1",
		"children" : [],
		"deviceCode" : "32021154001320012820D",
		"domain" : true,
		"domainId" : 4,
		"fullCheck" : true,
		"gpsX" : "120.255905000000",
		"gpsY" : "31.536001000000",
		"halfCheck" : false,
		"icon" : "rifle_channel",
		"id" : "32021154001320012820",
		"intelliState" : 0,
		"isFullCheck" : true,
		"isHalfCheck" : false,
		"isOnline" : true,
		"isParent" : false,
		"isSearched" : true,
		"mapType" : "",
		"name" : "瑞湖华庭二期南门车辆-ZH20",
		"nodeType" : 3,
		"notEnableEncoderChannel" : false,
		"online" : "1",
		"orgCode" : "32021154002160010968",
		"orgType" : "1",
		"paasId" : "152272379",
		"parent" : false,
		"parentId" : "32021154001320012820D",
		"parentNodeType" : 0,
		"platformCode" : "84816576869850244",
		"resourceCode" : "32021154001320012820",
		"resourceName" : "瑞湖华庭二期南门车辆-ZH20",
		"sn" : "32021154001320012820",
		"sort" : 0,
		"stat" : 1,
		"status" : 1,
		"statusTime" : 1692599047000,
		"subCount" : 0,
		"subType" : "2",
		"unitType" : "1"
	},
	{
		"accessSource" : "",
		"addType" : "",
		"cameraFunctions" : "",
		"cameraType" : "1",
		"category" : "1",
		"channelCode" : "32021154001320014758",
		"channelId" : "32021154001320014758",
		"channelName" : "瑞湖华庭一期北门双仓-ZH20",
		"channelSeq" : 0,
		"channelSn" : "32021154001320014758",
		"channelType" : "1",
		"children" : [],
		"deviceCode" : "32021154001320014758D",
		"domain" : true,
		"domainId" : 4,
		"fullCheck" : true,
		"gpsX" : "120.256201000000",
		"gpsY" : "31.536398000000",
		"halfCheck" : false,
		"icon" : "rifle_channel",
		"id" : "32021154001320014758",
		"intelliState" : 0,
		"isFullCheck" : true,
		"isHalfCheck" : false,
		"isOnline" : true,
		"isParent" : false,
		"isSearched" : true,
		"mapType" : "",
		"name" : "瑞湖华庭一期北门双仓-ZH20",
		"nodeType" : 3,
		"notEnableEncoderChannel" : false,
		"online" : "1",
		"orgCode" : "32021154002160010968",
		"orgType" : "1",
		"paasId" : "152272379",
		"parent" : false,
		"parentId" : "32021154001320014758D",
		"parentNodeType" : 0,
		"platformCode" : "84816576869850244",
		"resourceCode" : "32021154001320014758",
		"resourceName" : "瑞湖华庭一期北门双仓-ZH20",
		"sn" : "32021154001320014758",
		"sort" : 0,
		"stat" : 1,
		"status" : 1,
		"statusTime" : 1691123216000,
		"subCount" : 0,
		"subType" : "2",
		"unitType" : "1"
	},
	{
		"accessSource" : "",
		"addType" : "",
		"cameraFunctions" : "",
		"cameraType" : "1",
		"category" : "1",
		"channelCode" : "32021154001320016010",
		"channelId" : "32021154001320016010",
		"channelName" : "瑞湖华庭二期北门双仓-ZH20",
		"channelSeq" : 0,
		"channelSn" : "32021154001320016010",
		"channelType" : "1",
		"children" : [],
		"deviceCode" : "32021154001320016010D",
		"domain" : true,
		"domainId" : 4,
		"fullCheck" : true,
		"gpsX" : "120.255883000000",
		"gpsY" : "31.536366000000",
		"halfCheck" : false,
		"icon" : "rifle_channel",
		"id" : "32021154001320016010",
		"intelliState" : 0,
		"isFullCheck" : true,
		"isHalfCheck" : false,
		"isOnline" : true,
		"isParent" : false,
		"isSearched" : true,
		"mapType" : "",
		"name" : "瑞湖华庭二期北门双仓-ZH20",
		"nodeType" : 3,
		"notEnableEncoderChannel" : false,
		"online" : "1",
		"orgCode" : "32021154002160010968",
		"orgType" : "1",
		"paasId" : "152272379",
		"parent" : false,
		"parentId" : "32021154001320016010D",
		"parentNodeType" : 0,
		"platformCode" : "84816576869850244",
		"resourceCode" : "32021154001320016010",
		"resourceName" : "瑞湖华庭二期北门双仓-ZH20",
		"sn" : "32021154001320016010",
		"sort" : 0,
		"stat" : 1,
		"status" : 1,
		"statusTime" : 1691123216000,
		"subCount" : 0,
		"subType" : "2",
		"unitType" : "1"
	},
	{
		"accessSource" : "",
		"addType" : "",
		"cameraFunctions" : "",
		"cameraType" : "1",
		"category" : "1",
		"channelCode" : "32021154001320018239",
		"channelId" : "32021154001320018239",
		"channelName" : "瑞湖华庭二期南门双仓-ZH20",
		"channelSeq" : 0,
		"channelSn" : "32021154001320018239",
		"channelType" : "1",
		"children" : [],
		"deviceCode" : "32021154001320018239D",
		"domain" : true,
		"domainId" : 4,
		"fullCheck" : true,
		"gpsX" : "120.255960000000",
		"gpsY" : "31.535958000000",
		"halfCheck" : false,
		"icon" : "rifle_channel",
		"id" : "32021154001320018239",
		"intelliState" : 0,
		"isFullCheck" : true,
		"isHalfCheck" : false,
		"isOnline" : true,
		"isParent" : false,
		"isSearched" : true,
		"mapType" : "",
		"name" : "瑞湖华庭二期南门双仓-ZH20",
		"nodeType" : 3,
		"notEnableEncoderChannel" : false,
		"online" : "1",
		"orgCode" : "32021154002160010968",
		"orgType" : "1",
		"paasId" : "152272379",
		"parent" : false,
		"parentId" : "32021154001320018239D",
		"parentNodeType" : 0,
		"platformCode" : "84816576869850244",
		"resourceCode" : "32021154001320018239",
		"resourceName" : "瑞湖华庭二期南门双仓-ZH20",
		"sn" : "32021154001320018239",
		"sort" : 0,
		"stat" : 1,
		"status" : 1,
		"statusTime" : 1691123216000,
		"subCount" : 0,
		"subType" : "2",
		"unitType" : "1"
	},
	{
		"accessSource" : "",
		"addType" : "",
		"cameraFunctions" : "",
		"cameraType" : "1",
		"category" : "1",
		"channelCode" : "32021154001320018676",
		"channelId" : "32021154001320018676",
		"channelName" : "瑞湖华庭一期南门双仓-ZH20",
		"channelSeq" : 0,
		"channelSn" : "32021154001320018676",
		"channelType" : "1",
		"children" : [],
		"deviceCode" : "32021154001320018676D",
		"domain" : true,
		"domainId" : 4,
		"fullCheck" : true,
		"gpsX" : "120.256157000000",
		"gpsY" : "31.535996000000",
		"halfCheck" : false,
		"icon" : "rifle_channel",
		"id" : "32021154001320018676",
		"intelliState" : 0,
		"isFullCheck" : true,
		"isHalfCheck" : false,
		"isOnline" : true,
		"isParent" : false,
		"isSearched" : true,
		"mapType" : "",
		"name" : "瑞湖华庭一期南门双仓-ZH20",
		"nodeType" : 3,
		"notEnableEncoderChannel" : false,
		"online" : "1",
		"orgCode" : "32021154002160010968",
		"orgType" : "1",
		"paasId" : "152272379",
		"parent" : false,
		"parentId" : "32021154001320018676D",
		"parentNodeType" : 0,
		"platformCode" : "84816576869850244",
		"resourceCode" : "32021154001320018676",
		"resourceName" : "瑞湖华庭一期南门双仓-ZH20",
		"sn" : "32021154001320018676",
		"sort" : 0,
		"stat" : 1,
		"status" : 1,
		"statusTime" : 1692579465000,
		"subCount" : 0,
		"subType" : "2",
		"unitType" : "1"
	},
	{
		"accessSource" : "",
		"addType" : "",
		"cameraFunctions" : "",
		"cameraType" : "1",
		"category" : "1",
		"channelCode" : "32021154001320018737",
		"channelId" : "32021154001320018737",
		"channelName" : "瑞湖华庭二期北门双仓人脸-ZH20",
		"channelSeq" : 0,
		"channelSn" : "32021154001320018737",
		"channelType" : "1",
		"children" : [],
		"deviceCode" : "32021154001320018737D",
		"domain" : true,
		"domainId" : 4,
		"fullCheck" : true,
		"gpsX" : "120.255847000000",
		"gpsY" : "31.536469000000",
		"halfCheck" : false,
		"icon" : "rifle_channel",
		"id" : "32021154001320018737",
		"intelliState" : 0,
		"isFullCheck" : true,
		"isHalfCheck" : false,
		"isOnline" : true,
		"isParent" : false,
		"isSearched" : true,
		"mapType" : "",
		"name" : "瑞湖华庭二期北门双仓人脸-ZH20",
		"nodeType" : 3,
		"notEnableEncoderChannel" : false,
		"online" : "1",
		"orgCode" : "32021154002160010968",
		"orgType" : "1",
		"paasId" : "152272379",
		"parent" : false,
		"parentId" : "32021154001320018737D",
		"parentNodeType" : 0,
		"platformCode" : "84816576869850244",
		"resourceCode" : "32021154001320018737",
		"resourceName" : "瑞湖华庭二期北门双仓人脸-ZH20",
		"sn" : "32021154001320018737",
		"sort" : 0,
		"stat" : 1,
		"status" : 1,
		"statusTime" : 1691123216000,
		"subCount" : 0,
		"subType" : "2",
		"unitType" : "1"
	},
	{
		"accessSource" : "",
		"addType" : "",
		"cameraFunctions" : "",
		"cameraType" : "1",
		"category" : "1",
		"channelCode" : "32021154001320018739",
		"channelId" : "32021154001320018739",
		"channelName" : "瑞湖华庭二期北门车辆-ZH20",
		"channelSeq" : 0,
		"channelSn" : "32021154001320018739",
		"channelType" : "1",
		"children" : [],
		"deviceCode" : "32021154001320018739D",
		"domain" : true,
		"domainId" : 4,
		"fullCheck" : true,
		"gpsX" : "120.255863000000",
		"gpsY" : "31.536394000000",
		"halfCheck" : false,
		"icon" : "rifle_channel",
		"id" : "32021154001320018739",
		"intelliState" : 0,
		"isFullCheck" : true,
		"isHalfCheck" : false,
		"isOnline" : true,
		"isParent" : false,
		"isSearched" : true,
		"mapType" : "",
		"name" : "瑞湖华庭二期北门车辆-ZH20",
		"nodeType" : 3,
		"notEnableEncoderChannel" : false,
		"online" : "1",
		"orgCode" : "32021154002160010968",
		"orgType" : "1",
		"paasId" : "152272379",
		"parent" : false,
		"parentId" : "32021154001320018739D",
		"parentNodeType" : 0,
		"platformCode" : "84816576869850244",
		"resourceCode" : "32021154001320018739",
		"resourceName" : "瑞湖华庭二期北门车辆-ZH20",
		"sn" : "32021154001320018739",
		"sort" : 0,
		"stat" : 1,
		"status" : 1,
		"statusTime" : 1691123216000,
		"subCount" : 0,
		"subType" : "2",
		"unitType" : "1"
	},
	{
		"accessSource" : "",
		"addType" : "",
		"cameraFunctions" : "",
		"cameraType" : "1",
		"category" : "1",
		"channelCode" : "32021154001320019554",
		"channelId" : "32021154001320019554",
		"channelName" : "瑞湖华庭二期南门双仓人脸-ZH20",
		"channelSeq" : 0,
		"channelSn" : "32021154001320019554",
		"channelType" : "1",
		"children" : [],
		"deviceCode" : "32021154001320019554D",
		"domain" : true,
		"domainId" : 4,
		"fullCheck" : true,
		"gpsX" : "120.255949000000",
		"gpsY" : "31.535997000000",
		"halfCheck" : false,
		"icon" : "rifle_channel",
		"id" : "32021154001320019554",
		"intelliState" : 0,
		"isFullCheck" : true,
		"isHalfCheck" : false,
		"isOnline" : true,
		"isParent" : false,
		"isSearched" : true,
		"mapType" : "",
		"name" : "瑞湖华庭二期南门双仓人脸-ZH20",
		"nodeType" : 3,
		"notEnableEncoderChannel" : false,
		"online" : "1",
		"orgCode" : "32021154002160010968",
		"orgType" : "1",
		"paasId" : "152272379",
		"parent" : false,
		"parentId" : "32021154001320019554D",
		"parentNodeType" : 0,
		"platformCode" : "84816576869850244",
		"resourceCode" : "32021154001320019554",
		"resourceName" : "瑞湖华庭二期南门双仓人脸-ZH20",
		"sn" : "32021154001320019554",
		"sort" : 0,
		"stat" : 1,
		"status" : 1,
		"statusTime" : 1691123216000,
		"subCount" : 0,
		"subType" : "2",
		"unitType" : "1"
	},
	{
		"accessSource" : "",
		"addType" : "",
		"cameraFunctions" : "",
		"cameraType" : "1",
		"category" : "1",
		"channelCode" : "32021154001320019580",
		"channelId" : "32021154001320019580",
		"channelName" : "瑞湖华庭一期南门双仓人脸-ZH20",
		"channelSeq" : 0,
		"channelSn" : "32021154001320019580",
		"channelType" : "1",
		"children" : [],
		"deviceCode" : "32021154001320019580D",
		"domain" : true,
		"domainId" : 4,
		"fullCheck" : true,
		"gpsX" : "120.256201000000",
		"gpsY" : "31.536002000000",
		"halfCheck" : false,
		"icon" : "rifle_channel",
		"id" : "32021154001320019580",
		"intelliState" : 0,
		"isFullCheck" : true,
		"isHalfCheck" : false,
		"isOnline" : true,
		"isParent" : false,
		"isSearched" : true,
		"mapType" : "",
		"name" : "瑞湖华庭一期南门双仓人脸-ZH20",
		"nodeType" : 3,
		"notEnableEncoderChannel" : false,
		"online" : "1",
		"orgCode" : "32021154002160010968",
		"orgType" : "1",
		"paasId" : "152272379",
		"parent" : false,
		"parentId" : "32021154001320019580D",
		"parentNodeType" : 0,
		"platformCode" : "84816576869850244",
		"resourceCode" : "32021154001320019580",
		"resourceName" : "瑞湖华庭一期南门双仓人脸-ZH20",
		"sn" : "32021154001320019580",
		"sort" : 0,
		"stat" : 1,
		"status" : 1,
		"statusTime" : 1692579469000,
		"subCount" : 0,
		"subType" : "2",
		"unitType" : "1"
	}
]